uagen/__init__.py
uagen/uagen.py
uagen-0.0.1.dist-info/LICENSE
uagen-0.0.1.dist-info/METADATA
uagen-0.0.1.dist-info/WHEEL
uagen-0.0.1.dist-info/entry_points.txt
uagen-0.0.1.dist-info/top_level.txt
uagen-0.0.1.dist-info/RECORD
