Metadata-Version: 2.1
Name: uagen
Version: 0.0.1
Summary: A tool to generate a random user_agent
Home-page: https://github.com/ga1008/uagen
Author: Guardian
Author-email: zhling2012@live.com
Maintainer: Guardian
Maintainer-email: zhling2012@live.com
License: UNKNOWN
Platform: UNKNOWN
Classifier: Programming Language :: Python :: 3
Classifier: License :: OSI Approved :: MIT License
Classifier: Operating System :: OS Independent
Requires-Dist: argparse
